.DS_Store
gwsnr/__init__.py
gwsnr/_version.py
gwsnr/ann_model_generator.py
gwsnr/gwsnr copy.py
gwsnr/gwsnr.py
gwsnr/gwsnr_old.py
gwsnr/jaxjit_functions.py
gwsnr/multiprocessing_routine.py
gwsnr/njit_functions.py
gwsnr/pdet.py
gwsnr/ripple_class.py
gwsnr/utils.py
gwsnr/ann/__init__.py
gwsnr/ann/ann_model_H1_O4.h5
gwsnr/ann/ann_model_L1_O4.h5
gwsnr/ann/ann_model_V1_O4.h5
gwsnr/ann/ann_model_generator.py
gwsnr/ann/ann_path_dict.json
gwsnr/ann/error_adjustment_H1_O4.json
gwsnr/ann/error_adjustment_L1_O4.json
gwsnr/ann/error_adjustment_V1_O4.json
gwsnr/ann/scaler_H1_O4.pkl
gwsnr/ann/scaler_L1_O4.pkl
gwsnr/ann/scaler_V1_O4.pkl
gwsnr/ann/ann_data/ann_model_H1.h5
gwsnr/ann/ann_data/ann_model_L1.h5
gwsnr/ann/ann_data/ann_model_V1.h5
gwsnr/ann/ann_data/ann_path_dict.json
gwsnr/ann/ann_data/error_adjustment_H1.json
gwsnr/ann/ann_data/error_adjustment_L1.json
gwsnr/ann/ann_data/error_adjustment_V1.json
gwsnr/ann/ann_data/scaler_H1.pkl
gwsnr/ann/ann_data/scaler_L1.pkl
gwsnr/ann/ann_data/scaler_V1.pkl
gwsnr/core/__init__.py
gwsnr/core/gwsnr.py
gwsnr/core/interpolator_pickle/CE/param_dict_list.pickle
gwsnr/core/interpolator_pickle/CE/partialSNR_dict_0.pickle
gwsnr/core/interpolator_pickle/ET1/param_dict_list.pickle
gwsnr/core/interpolator_pickle/ET1/partialSNR_dict_0.pickle
gwsnr/core/interpolator_pickle/ET2/param_dict_list.pickle
gwsnr/core/interpolator_pickle/ET2/partialSNR_dict_0.pickle
gwsnr/core/interpolator_pickle/ET3/param_dict_list.pickle
gwsnr/core/interpolator_pickle/ET3/partialSNR_dict_0.pickle
gwsnr/core/interpolator_pickle/H1/param_dict_list.pickle
gwsnr/core/interpolator_pickle/H1/partialSNR_dict_0.pickle
gwsnr/core/interpolator_pickle/H1/partialSNR_dict_1.pickle
gwsnr/core/interpolator_pickle/H1/partialSNR_dict_2.pickle
gwsnr/core/interpolator_pickle/L1/param_dict_list.pickle
gwsnr/core/interpolator_pickle/L1/partialSNR_dict_0.pickle
gwsnr/core/interpolator_pickle/L1/partialSNR_dict_1.pickle
gwsnr/core/interpolator_pickle/L1/partialSNR_dict_2.pickle
gwsnr-0.3.7.dist-info/METADATA
gwsnr-0.3.7.dist-info/WHEEL
gwsnr-0.3.7.dist-info/top_level.txt
gwsnr-0.3.7.dist-info/RECORD
