Metadata-Version: 2.4
Name: gwsnr
Version: 0.3.7
Summary: A Python package for calculating gravitational wave signal-to-noise ratios
Home-page: https://github.com/hemantaph/gwsnr
Author: Hemantakumar Phurailatpam
Author-email: Hemantakumar Phurailatpam <hemantaphurailatpam@gmail.com>
Maintainer-email: Hemantakumar Phurailatpam <hemantaphurailatpam@gmail.com>
License: MIT
Project-URL: Homepage, https://github.com/hemantaph/gwsnr
Project-URL: Documentation, https://gwsnr.readthedocs.io
Project-URL: Repository, https://github.com/hemantaph/gwsnr
Project-URL: Bug Tracker, https://github.com/hemantaph/gwsnr/issues
Keywords: gravitational-waves,signal-processing,physics,astronomy
Classifier: Development Status :: 4 - Beta
Classifier: Intended Audience :: Science/Research
Classifier: License :: OSI Approved :: MIT License
Classifier: Programming Language :: Python :: 3
Classifier: Programming Language :: Python :: 3.10
Classifier: Programming Language :: Python :: 3.11
Classifier: Programming Language :: Python :: 3.12
Classifier: Topic :: Scientific/Engineering :: Physics
Classifier: Topic :: Scientific/Engineering :: Astronomy
Requires-Python: >=3.10
Requires-Dist: setuptools>=80.9.0
Requires-Dist: astropy>=6.1.7
Requires-Dist: bilby>=2.5.2
Requires-Dist: corner>=2.2.3
Requires-Dist: gwpy>=3.0.12
Requires-Dist: h5py>=3.11.0
Requires-Dist: lalsuite>=7.26.1
Requires-Dist: numba>=0.61.2
Requires-Dist: numpy>=1.26.4
Requires-Dist: pandas>=2.3.0
Requires-Dist: scipy>=1.15.3
Requires-Dist: tqdm>=4.67.1
Dynamic: author
Dynamic: home-page
Dynamic: requires-python
